netpackets/__init__.py
netpackets/ethernet.py
netpackets/ipv4.py
netpackets/packet.py
netpackets/tcp.py
netpackets-1.0.3.dist-info/LICENSE
netpackets-1.0.3.dist-info/METADATA
netpackets-1.0.3.dist-info/WHEEL
netpackets-1.0.3.dist-info/top_level.txt
netpackets-1.0.3.dist-info/RECORD
