Metadata-Version: 2.1
Name: netpackets
Version: 1.0.3
Summary: Network packets constructor
License:                     GNU GENERAL PUBLIC LICENSE
Requires-Python: >=3.8
License-File: LICENSE
